piotr/__init__.py
piotr/api.py
piotr/device.py
piotr/package.py
piotr/shell.py
piotr/test.py
piotr/user.py
piotr/cmdline/__init__.py
piotr/cmdline/device.py
piotr/cmdline/dtb.py
piotr/cmdline/fs.py
piotr/cmdline/kernel.py
piotr/cmdline/showall.py
piotr/data/config.skeleton.yaml
piotr/data/virt.cortex-a7.little-5.10.7
piotr/data/virt.cortex-a7.little-5.10.7.ext2
piotr/exceptions/__init__.py
piotr/qemu/__init__.py
piotr/qemu/guest.py
piotr/qemu/platform.py
piotr/qemu/virt.py
piotr/util/__init__.py
piotr/util/cmdparser.py
piotr/util/device.py
piotr/util/dtb.py
piotr/util/hostfs.py
piotr/util/kernel.py
piotr/util/logger.py
piotr/util/namegen.py
piotr/util/qemu/__init__.py
piotr/util/qemu/accel.py
piotr/util/qemu/agent.py
piotr/util/qemu/machine.py
piotr/util/qemu/qmp.py
piotr/util/qemu/qtest.py
piotr-1.0.2.dist-info/LICENSE
piotr-1.0.2.dist-info/METADATA
piotr-1.0.2.dist-info/WHEEL
piotr-1.0.2.dist-info/entry_points.txt
piotr-1.0.2.dist-info/top_level.txt
piotr-1.0.2.dist-info/RECORD
