Metadata-Version: 2.1
Name: piotr
Version: 1.0.2
Summary: Piotr is an instrumentation tool for qemu-system-arm able to emulate ARM-based embedded devices.
Home-page: https://github.com/virtualabs/piotr
Author: virtualabs
Author-email: virtualabs@gmail.com
License: UNKNOWN
Platform: UNKNOWN
Classifier: License :: OSI Approved :: MIT License
Classifier: Operating System :: POSIX :: Linux
Classifier: Development Status :: 4 - Beta
Requires-Python: >=3.5
License-File: LICENSE
Requires-Dist: blessings
Requires-Dist: psutil
Requires-Dist: pyyaml
